[{"title":"Whole beans","imageUrl":"https://images-na.ssl-images-amazon.com/images/I/71Nb6BXaQPL._SX425_.jpg","description":"49","price":"FIRST-PLACE AWARD WINNING 100% PURE KONA GOLD COFFEE BEANS, FROM OUR OHANA TO YOURS 100% Kona Coffee is one of the world's finest specialty coffees"},{"title":"Whole beans","imageUrl":"https://images-na.ssl-images-amazon.com/images/I/71%2BOyi3WOYL._SL1500_.jpg","description":"49.99","price":"dddddddddddddddddddddddd"},{"title":"Whole beans","imageUrl":"https://images.costco-static.com/ImageDelivery/imageService?profileId=12026540&itemId=1381390-847&recipeName=680","description":"29.99","price":"A blend of dark and medium roasted “specialty grade” USDA Organic South and Central American coffee beans."}]